grabseqs-1.0.0.dist-info/licenses/LICENSE
grabseqslib/__init__.py
grabseqslib/mgrast.py
grabseqslib/sra.py
grabseqslib/utils.py
grabseqs-1.0.0.dist-info/METADATA
grabseqs-1.0.0.dist-info/WHEEL
grabseqs-1.0.0.dist-info/entry_points.txt
grabseqs-1.0.0.dist-info/top_level.txt
grabseqs-1.0.0.dist-info/RECORD
