Metadata-Version: 2.4
Name: grabseqs
Version: 1.0.0
Summary: Easily download reads from next-gen sequencing repositories like NCBI SRA
Home-page: https://github.com/louiejtaylor/grabseqs
Author: Louis J Taylor
Author-email: louist@upenn.edu
License: MIT License
Classifier: Intended Audience :: Science/Research
Classifier: Environment :: Console
Classifier: Environment :: Web Environment
Classifier: License :: OSI Approved :: MIT License
Classifier: Programming Language :: Python :: 3
Classifier: Topic :: Scientific/Engineering :: Bio-Informatics
License-File: LICENSE
Requires-Dist: requests
Requires-Dist: argparse
Requires-Dist: pandas>=2
Dynamic: author
Dynamic: author-email
Dynamic: classifier
Dynamic: home-page
Dynamic: license
Dynamic: license-file
Dynamic: requires-dist
Dynamic: summary
